faultsim/__init__.py
faultsim-0.0.1.dist-info/LICENSE
faultsim-0.0.1.dist-info/METADATA
faultsim-0.0.1.dist-info/WHEEL
faultsim-0.0.1.dist-info/top_level.txt
faultsim-0.0.1.dist-info/RECORD
