Metadata-Version: 2.1
Name: faultsim
Version: 0.0.1
Summary: Basic combinational logic circuit fault simulation
Home-page: https://github.com/immaxchen/faultsim
Author: Max Chen
Author-email: immaxchen@gmail.com
License: UNKNOWN
Platform: UNKNOWN
Classifier: Programming Language :: Python :: 3
Classifier: License :: OSI Approved :: MIT License
Classifier: Operating System :: OS Independent
Requires-Python: >=3.6
License-File: LICENSE
